sales_analyzer/__init__.py
sales_analyzer/analyze.py
sales_analyzer/cli.py
sales_analyzer-0.1.0.dist-info/METADATA
sales_analyzer-0.1.0.dist-info/WHEEL
sales_analyzer-0.1.0.dist-info/entry_points.txt
sales_analyzer-0.1.0.dist-info/top_level.txt
sales_analyzer-0.1.0.dist-info/RECORD
