Metadata-Version: 2.1
Name: sales-analyzer
Version: 0.1.0
Summary: A package to analyze sales data
Author-email: Grigory <grig.perev@gmail.com>
License: MIT
Requires-Python: >=3.7
